bwrapper/__init__.py
bwrapper/boto.py
bwrapper/jobsy.py
bwrapper/json_utils.py
bwrapper/log.py
bwrapper/notsy.py
bwrapper/run_loop.py
bwrapper/sns.py
bwrapper/sqs.py
bwrapper-0.7.0.dist-info/LICENSE
bwrapper-0.7.0.dist-info/METADATA
bwrapper-0.7.0.dist-info/WHEEL
bwrapper-0.7.0.dist-info/top_level.txt
bwrapper-0.7.0.dist-info/RECORD
