Metadata-Version: 2.1
Name: bwrapper
Version: 0.7.0
Summary: It is what it is.
Home-page: https://github.com/jbasko/bwrapper
Author: Jazeps Basko
Author-email: jazeps.basko@gmail.com
License: MIT license
Keywords: bwrapper
Platform: UNKNOWN
Classifier: Development Status :: 2 - Pre-Alpha
Classifier: Intended Audience :: Developers
Classifier: License :: OSI Approved :: MIT License
Classifier: Natural Language :: English
Classifier: Programming Language :: Python :: 3
Classifier: Programming Language :: Python :: 3.6
Classifier: Programming Language :: Python :: 3.7
Classifier: Programming Language :: Python :: 3.8
Requires-Python: >=3.6
Requires-Dist: boto3
